pwh_pyramid_routes/__init__.py
pwh_pyramid_routes-1.0.0.dist-info/WHEEL
pwh_pyramid_routes-1.0.0.dist-info/METADATA
pwh_pyramid_routes-1.0.0.dist-info/RECORD
