Metadata-Version: 2.1
Name: pwh-pyramid-routes
Version: 1.0.0
Summary: Route helpers for Pyramid
License: MIT
Author: Mark Hall
Author-email: mark.hall@work.room3b.eu
Requires-Python: >=3.7,<4.0
Classifier: License :: OSI Approved :: MIT License
Classifier: Programming Language :: Python :: 3
Classifier: Programming Language :: Python :: 3.7
Classifier: Programming Language :: Python :: 3.8
Requires-Dist: decorator (>=4.4.2,<5.0.0)
Requires-Dist: pyramid_jinja2 (>=2.8,<3.0)
